[
  {
    "fields": [
      {
        "initialValue": "Cherry Cigarette Productions",
        "description": "The site title displayed in the browser tab",
        "name": "siteTitle",
        "type": "string"
      },
      {
        "options": {
          "accept": ".ico"
        },
        "description": "Main favicon file (.ico format)",
        "name": "favicon",
        "type": "image",
        "title": "Favicon (.ico)"
      },
      {
        "options": {
          "accept": ".png"
        },
        "description": "Favicon 16x16 PNG",
        "name": "favicon16",
        "type": "image",
        "title": "Favicon 16x16"
      },
      {
        "options": {
          "accept": ".png"
        },
        "description": "Favicon 32x32 PNG",
        "name": "favicon32",
        "type": "image",
        "title": "Favicon 32x32"
      },
      {
        "options": {
          "accept": ".png"
        },
        "description": "Android Chrome icon 192x192 PNG",
        "name": "androidChrome192",
        "type": "image",
        "title": "Android Chrome 192x192"
      },
      {
        "options": {
          "accept": ".png"
        },
        "description": "Android Chrome icon 512x512 PNG",
        "name": "androidChrome512",
        "type": "image",
        "title": "Android Chrome 512x512"
      },
      {
        "options": {
          "accept": ".png"
        },
        "description": "Apple Touch Icon PNG",
        "name": "appleTouchIcon",
        "type": "image"
      },
      {
        "description": "Company bio/description",
        "name": "bio",
        "type": "text"
      },
      {
        "rows": 3,
        "description": "SEO meta description (falls back to Bio if not set)",
        "name": "metaDescription",
        "type": "text"
      },
      {
        "description": "SEO meta keywords (comma-separated)",
        "name": "metaKeywords",
        "type": "string"
      },
      {
        "initialValue": "CONTACT",
        "description": "Contact section label (e.g., \"CONTACT\")",
        "name": "contact",
        "type": "string",
        "title": "Contact Label"
      },
      {
        "description": "Contact email address",
        "name": "email",
        "type": "string"
      },
      {
        "initialValue": 10,
        "validation": [
          {
            "rules": [
              {
                "flag": "min",
                "constraint": 1
              },
              {
                "flag": "max",
                "constraint": 60
              }
            ],
            "level": "error"
          }
        ],
        "description": "Duration of the smoking effect in seconds",
        "name": "smokingDuration",
        "type": "number",
        "title": "Smoking Effect Duration"
      },
      {
        "initialValue": 3,
        "validation": [
          {
            "rules": [
              {
                "flag": "min",
                "constraint": 1
              },
              {
                "flag": "max",
                "constraint": 10
              }
            ],
            "level": "error"
          }
        ],
        "description": "How much faster the line burns while holding mouse click (1-10)",
        "name": "burnAccelerationFactor",
        "type": "number"
      }
    ],
    "name": "landingPage",
    "type": "document"
  }
]